rsgym/__init__.py
rsgym/wrappers/__init__.py
rsgym/wrappers/gym_wrappers.py
rslearn/__init__.py
rslearn/datasets/__init__.py
rslearn/datasets/eai/__init__.py
rslearn/datasets/eai/alfred.py
rslearn/datasets/eai/habitat.py
rslearn/datasets/image_classification/__init__.py
rslearn/datasets/image_classification/cifar.py
rslearn/datasets/image_classification/mnist.py
rslearn/datasets/image_classification/svhn.py
rslearn/datasets/vqa/__init__.py
rsmlkit/__init__.py
rsmlkit/cli/__init__.py
rsmlkit/cli/keyboard.py
rsmlkit/collections/__init__.py
rsmlkit/collections/frozendict.py
rsmlkit/concurrency/__init__.py
rsmlkit/concurrency/process.py
rsmlkit/io/__init__.py
rsmlkit/io/common.py
rsmlkit/io/network.py
rsmlkit/logging/__init__.py
rsmlkit/logging/exception.py
rsmlkit/logging/logger.py
rsmlkit/misc/__init__.py
rsmlkit/random/__init__.py
rsmlkit/utils/__init__.py
rsmlkit/utils/cache.py
rsmlkit/utils/decorators.py
rsmlkit/utils/deprecated.py
rsmlkit/utils/import_helper.py
rsmlkit/utils/meta.py
rsmlkit/utils/network.py
rsmlkit/utils/tqdm.py
rsmltorch/__init__.py
rsmltorch/repr/__init__.py
rsmltorch/repr/misc.py
rsnumpy/__init__.py
rsnumpy/utils/__init__.py
rsnumpy/utils/list2np.py
rstorch/__init__.py
rstorch/repr/__init__.py
rstorch/repr/misc.py
rsmlkit-0.0.11.dist-info/METADATA
rsmlkit-0.0.11.dist-info/WHEEL
rsmlkit-0.0.11.dist-info/top_level.txt
rsmlkit-0.0.11.dist-info/RECORD
